{
  "results": [
    {
      "username": "EXPRESSO",
      "text": "express",
      "roomname": "lobby",
      "objectId": 0
    },
    {
      "username": "EXPRESSO",
      "text": "EXPRESSOLY",
      "roomname": "lobby",
      "objectId": 1
    },
    {
      "username": "EXPRESSO",
      "text": "we're done!!",
      "roomname": "lobby",
      "objectId": 2
    },
    {
      "username": "EXPRESSO",
      "text": "final test",
      "roomname": "lobby",
      "objectId": 3
    },
    {
      "username": "EXPRESSO",
      "text": "one more test",
      "roomname": "lobby",
      "objectId": 4
    }
  ]
}